<?xml version="1.0" encoding="UTF-8"?>
<mule xmlns:ee="http://www.mulesoft.org/schema/mule/ee/core"
    xmlns:http="http://www.mulesoft.org/schema/mule/http"
    xmlns="http://www.mulesoft.org/schema/mule/core" xmlns:doc="http://www.mulesoft.org/schema/mule/documentation"
    xmlns:xsi="http://www.w3.org/2001/XMLSchema-instance"
    xsi:schemaLocation="
http://www.mulesoft.org/schema/mule/ee/core http://www.mulesoft.org/schema/mule/ee/core/current/mule-ee.xsd 
http://www.mulesoft.org/schema/mule/http http://www.mulesoft.org/schema/mule/http/current/mule-http.xsd http://www.mulesoft.org/schema/mule/core http://www.mulesoft.org/schema/mule/core/current/mule.xsd">

    <sub-flow name="get-customers-business-flow" doc:id="business-flow" doc:name="Get Customers Business Logic">
        <logger level="INFO" doc:name="Log Business Start" message="Entering business orchestration for customer retrieval..."/>
        
        <!-- Simulate a Backend System Call using the shared configuration standards -->
        <http:request method="GET" doc:name="Call System API" 
            config-ref="HTTP_Request_configuration" 
            path="/customers" 
            responseTimeout="${http.responseTimeout}">
            <http:headers>#[{"x-correlation-id": vars.correlationId}]</http:headers>
        </http:request>

        <!-- Use DataWeave from external file -->
        <ee:transform doc:name="Transform Result" doc:id="transform">
            <ee:message>
                <ee:set-payload resource="dwl/transform-customer-response.dwl" />
            </ee:message>
        </ee:transform>

        <logger level="INFO" doc:name="Log Business End" message="Business orchestration complete."/>
    </sub-flow>

    <http:request-config name="HTTP_Request_configuration" doc:name="HTTP Request configuration">
        <http:request-connection host="${backend.system-papi.host}" port="${backend.system-papi.port}" protocol="HTTPS"/>
    </http:request-config>

</mule>
